cripto_ade2583b6b098c2208b8c9293402a29c431831b8/__init__.py
cripto_ade2583b6b098c2208b8c9293402a29c431831b8/main.py
cripto_ade2583b6b098c2208b8c9293402a29c431831b8-0.1.1.dist-info/licenses/LICENSE.txt
cripto_ade2583b6b098c2208b8c9293402a29c431831b8-0.1.1.dist-info/METADATA
cripto_ade2583b6b098c2208b8c9293402a29c431831b8-0.1.1.dist-info/WHEEL
cripto_ade2583b6b098c2208b8c9293402a29c431831b8-0.1.1.dist-info/entry_points.txt
cripto_ade2583b6b098c2208b8c9293402a29c431831b8-0.1.1.dist-info/top_level.txt
cripto_ade2583b6b098c2208b8c9293402a29c431831b8-0.1.1.dist-info/RECORD
