Metadata-Version: 2.4
Name: cripto-ade2583b6b098c2208b8c9293402a29c431831b8
Version: 0.1.1
Summary: Herramienta de pentesting
Author-email: Kovax00 <tuemail@ejemplo.com>
License-Expression: MIT
Requires-Python: >=3.8
License-File: LICENSE.txt
Dynamic: license-file
